README
setup.py
flask_jsonify_emidln.egg-info/PKG-INFO
flask_jsonify_emidln.egg-info/SOURCES.txt
flask_jsonify_emidln.egg-info/dependency_links.txt
flask_jsonify_emidln.egg-info/namespace_packages.txt
flask_jsonify_emidln.egg-info/not-zip-safe
flask_jsonify_emidln.egg-info/requires.txt
flask_jsonify_emidln.egg-info/top_level.txt
flaskext/__init__.py
flaskext/jsonify.py