Metadata-Version: 1.1
Name: flask-jsonify-emidln
Version: 0.1
Summary: A small Flask decorator for returning json. This is a fork pushed to PyPI for easy install.
Home-page: http://github.com/emidln/flask-jsonify
Author: Frederic Junod
Author-email: frederic.junod@gmail.com
License: BSD
Platform: any
Classifier: Development Status :: 4 - Beta
Classifier: Environment :: Web Environment
Classifier: Intended Audience :: Developers
Classifier: License :: OSI Approved :: BSD License
Classifier: Operating System :: OS Independent
Classifier: Programming Language :: Python
Classifier: Topic :: Internet :: WWW/HTTP :: Dynamic Content
Classifier: Topic :: Software Development :: Libraries :: Python Modules
